mcp_zammad/__init__.py
mcp_zammad/__main__.py
mcp_zammad/client.py
mcp_zammad/models.py
mcp_zammad/server.py
mseep_mcp_zammad-0.1.6.dist-info/METADATA
mseep_mcp_zammad-0.1.6.dist-info/WHEEL
mseep_mcp_zammad-0.1.6.dist-info/entry_points.txt
mseep_mcp_zammad-0.1.6.dist-info/licenses/LICENSE
mseep_mcp_zammad-0.1.6.dist-info/RECORD
